trubrics_beta/__init__.py
trubrics_beta/main.py
trubrics_beta-0.3.0.dist-info/METADATA
trubrics_beta-0.3.0.dist-info/WHEEL
trubrics_beta-0.3.0.dist-info/top_level.txt
trubrics_beta-0.3.0.dist-info/RECORD
