Metadata-Version: 2.1
Name: trubrics-beta
Version: 0.3.0
Summary: Python SDK to track events in Trubrics.
Author-email: Jeff Kayne <jeff.kayne@trubrics.com>
Classifier: Programming Language :: Python :: 3
Classifier: Operating System :: OS Independent
Requires-Python: >=3.8
